chevy/__init__.py
chevy/features.py
chevy/tests/__init__.py
chevy/tests/test_board_common_features.py
chevy/tests/test_king_safety.py
chevy/tests/test_pawn_structure.py
chevy/utils.py
chevy-0.2.2.dist-info/LICENSE
chevy-0.2.2.dist-info/WHEEL
chevy-0.2.2.dist-info/METADATA
chevy-0.2.2.dist-info/RECORD
