Metadata-Version: 2.1
Name: chevy
Version: 0.2.2
Summary: Chess position Evaluation via hand-crafted features
Home-page: https://github.com/int8/chevy
Keywords: chess,evaluation
Author: int8
Requires-Python: >=3.7,<3.11
Classifier: Programming Language :: Python :: 3
Classifier: Programming Language :: Python :: 3.10
Classifier: Programming Language :: Python :: 3.7
Classifier: Programming Language :: Python :: 3.8
Classifier: Programming Language :: Python :: 3.9
Requires-Dist: cachetools (>=5.2.0,<6.0.0)
Requires-Dist: msgpack (>=1.0.4,<2.0.0)
Requires-Dist: numpy (>=1.22.3,<2.0.0)
Requires-Dist: python-chess (>=1.999,<2.0)
Requires-Dist: scipy (>=1.8.0,<2.0.0)
Project-URL: Repository, https://github.com/int8/chevy
